mathcube/__init__.py
mathcube/equation.py
mathcube/geometry.py
mathcube/output.py
mathcube/stepbystep/__init__.py
mathcube/stepbystep/polynomials.py
tests/__init__.py
tests/test_equation.py
tests/test_output.py
mathcube-0.1.1.dist-info/LICENSE
mathcube-0.1.1.dist-info/METADATA
mathcube-0.1.1.dist-info/WHEEL
mathcube-0.1.1.dist-info/top_level.txt
mathcube-0.1.1.dist-info/RECORD
